pyglplot/__init__.py
pyglplot/common.py
pyglplot/line.py
pyglplot/roll.py
pyglplot/scatter.py
pyglplot-0.1.3.dist-info/METADATA
pyglplot-0.1.3.dist-info/WHEEL
pyglplot-0.1.3.dist-info/licenses/LICENSE
pyglplot-0.1.3.dist-info/RECORD
