Metadata-Version: 2.1
Name: pyglplot
Version: 0.1.3
Summary: A Python package for plotting.
Project-URL: Homepage, https://github.com/danchitnis/pyglplot
Project-URL: Bug Tracker, https://github.com/danchitnis/pyglplot/issues
Author-email: Danial Chitnis <d.chitnis@ed.ac.uk>
License-File: LICENSE
Classifier: License :: OSI Approved :: MIT License
Classifier: Operating System :: OS Independent
Classifier: Programming Language :: Python :: 3
Requires-Python: >=3.7
Requires-Dist: glfw
Requires-Dist: numpy
Requires-Dist: pyopengl
